[{"aqi":162,"area":"唐山","co":1.267,"co_24h":1.656,"no2":62,"no2_24h":81,"o3":161,"o3_24h":161,"o3_8h":90,"o3_8h_24h":134,"pm10":217,"pm10_24h":201,"pm2_5":123,"pm2_5_24h":122,"position_name":"供销社","primary_pollutant":"细颗粒物(PM2.5)","quality":"中度污染","so2":57,"so2_24h":52,"station_code":"1036A","time_point":"2016-03-17T16:00:00Z"},{"aqi":172,"area":"唐山","co":1.826,"co_24h":2.067,"no2":85,"no2_24h":87,"o3":147,"o3_24h":147,"o3_8h":90,"o3_8h_24h":132,"pm10":227,"pm10_24h":183,"pm2_5":130,"pm2_5_24h":124,"position_name":"雷达站","primary_pollutant":"细颗粒物(PM2.5)","quality":"中度污染","so2":60,"so2_24h":55,"station_code":"1037A","time_point":"2016-03-17T16:00:00Z"},{"aqi":170,"area":"唐山","co":1.54,"co_24h":2.021,"no2":65,"no2_24h":67,"o3":140,"o3_24h":140,"o3_8h":78,"o3_8h_24h":119,"pm10":230,"pm10_24h":200,"pm2_5":129,"pm2_5_24h":117,"position_name":"物资局","primary_pollutant":"细颗粒物(PM2.5)","quality":"中度污染","so2":48,"so2_24h":48,"station_code":"1038A","time_point":"2016-03-17T16:00:00Z"},{"aqi":179,"area":"唐山","co":1.674,"co_24h":2.676,"no2":67,"no2_24h":93,"o3":156,"o3_24h":156,"o3_8h":88,"o3_8h_24h":124,"pm10":217,"pm10_24h":218,"pm2_5":135,"pm2_5_24h":134,"position_name":"陶瓷公司","primary_pollutant":"细颗粒物(PM2.5)","quality":"中度污染","so2":54,"so2_24h":67,"station_code":"1039A","time_point":"2016-03-17T16:00:00Z"},{"aqi":208,"area":"唐山","co":1.483,"co_24h":1.912,"no2":74,"no2_24h":85,"o3":151,"o3_24h":151,"o3_8h":89,"o3_8h_24h":129,"pm10":211,"pm10_24h":200,"pm2_5":158,"pm2_5_24h":143,"position_name":"十二中","primary_pollutant":"细颗粒物(PM2.5)","quality":"重度污染","so2":63,"so2_24h":64,"station_code":"1040A","time_point":"2016-03-17T16:00:00Z"},{"aqi":218,"area":"唐山","co":1.442,"co_24h":2.135,"no2":59,"no2_24h":85,"o3":167,"o3_24h":167,"o3_8h":95,"o3_8h_24h":136,"pm10":240,"pm10_24h":214,"pm2_5":168,"pm2_5_24h":148,"position_name":"小山","primary_pollutant":"细颗粒物(PM2.5)","quality":"重度污染","so2":56,"so2_24h":58,"station_code":"1041A","time_point":"2016-03-17T16:00:00Z"},{"aqi":186,"area":"唐山","co":1.539,"co_24h":2.078,"no2":68,"no2_24h":83,"o3":153,"o3_24h":153,"o3_8h":88,"o3_8h_24h":129,"pm10":223,"pm10_24h":202,"pm2_5":140,"pm2_5_24h":131,"position_name":null,"primary_pollutant":"颗粒物(PM2.5)","quality":"中度污染","so2":56,"so2_24h":57,"station_code":null,"time_point":"2016-03-17T16:00:00Z"}]